duplicator/__init__.py
duplicator/admin.py
duplicator/apps.py
duplicator/models.py
duplicator/templates/admin/duplicator/change_form.html
duplicator/tests/__init__.py
duplicator/tests/dummy_models.py
duplicator/tests/settings.py
duplicator/tests/test_admin.py
duplicator/tests/test_models.py
duplicator/tests/urls.py
django_duplicator-0.1.4.dist-info/METADATA
django_duplicator-0.1.4.dist-info/WHEEL
django_duplicator-0.1.4.dist-info/licenses/LICENSE
django_duplicator-0.1.4.dist-info/RECORD
