Metadata-Version: 2.4
Name: django-duplicator
Version: 0.1.4
Summary: A reusable Django app to easily duplicate model records.
License: MIT
License-File: LICENSE
Keywords: django,admin,mixin,djang-duplicator,bulk-action
Author: Ferdina Kusumah
Author-email: ferdina.kusumah@gmail.com
Requires-Python: >=3.8,<4.0
Classifier: Framework :: Django
Classifier: Framework :: Django :: 3.2
Classifier: Framework :: Django :: 4.2
Classifier: Framework :: Django :: 5.0
Classifier: License :: OSI Approved :: MIT License
Classifier: Operating System :: OS Independent
Classifier: Programming Language :: Python :: 3
Classifier: Programming Language :: Python :: 3.8
Classifier: Programming Language :: Python :: 3.9
Classifier: Programming Language :: Python :: 3.10
Classifier: Programming Language :: Python :: 3.11
Classifier: Programming Language :: Python :: 3.12
Classifier: Programming Language :: Python :: 3.13
Classifier: Programming Language :: Python :: 3.14
Classifier: Topic :: Internet :: WWW/HTTP
Classifier: Topic :: Software Development :: Libraries :: Python Modules
Requires-Dist: Django (>=3.2)
Project-URL: Homepage, https://github.com/FerdinaKusumah/duplicator
Project-URL: Repository, https://github.com/FerdinaKusumah/duplicator
